setup.py
django_redis_sentinel/__init__.py
django_redis_sentinel/sentinel.py
django_redis_sentinel.egg-info/PKG-INFO
django_redis_sentinel.egg-info/SOURCES.txt
django_redis_sentinel.egg-info/dependency_links.txt
django_redis_sentinel.egg-info/not-zip-safe
django_redis_sentinel.egg-info/pbr.json
django_redis_sentinel.egg-info/requires.txt
django_redis_sentinel.egg-info/top_level.txt